test_data_generator/__init__.py
test_data_generator/generator.py
test_data_generator/generators.py
test_data_generator/load_schema.py
test_data_generator/schema.py
test_data_generator-0.1.1.dist-info/METADATA
test_data_generator-0.1.1.dist-info/WHEEL
test_data_generator-0.1.1.dist-info/licenses/LICENSE
test_data_generator-0.1.1.dist-info/RECORD
