Metadata-Version: 2.4
Name: test-data-generator
Version: 0.1.1
Summary: Deterministic test data generator from JSON schemas for consistent, repeatable testing
License: MIT
License-File: LICENSE
Keywords: testing,test-data,fixtures,generator,deterministic,schema,json
Author: Achanta Venkata
Author-email: satya.achantavenkata@gmail.com
Requires-Python: >=3.11
Classifier: Development Status :: 4 - Beta
Classifier: Intended Audience :: Developers
Classifier: Topic :: Software Development :: Testing
Classifier: License :: OSI Approved :: MIT License
Classifier: Programming Language :: Python :: 3
Classifier: Programming Language :: Python :: 3.11
Classifier: Programming Language :: Python :: 3.12
Classifier: Programming Language :: Python :: 3.13
Classifier: Programming Language :: Python :: 3.14
Classifier: Operating System :: OS Independent
Classifier: Typing :: Typed
Project-URL: Bug Tracker, https://github.com/satyaachanta/test-data-generator/issues
Project-URL: Documentation, https://github.com/satyaachanta/test-data-generator#readme
Project-URL: Homepage, https://github.com/satyaachanta/test-data-generator
Project-URL: Repository, https://github.com/satyaachanta/test-data-generator
